{"title":"Teargas and Plateglass- Self-Titled album and Black Triage","uid":6359889,"size":221940241,"categoryP":"audio","categoryS":"music","magnet":"?xt=urn:btih:2a33e25f18ece2ac5cd417935d627bbf303ffd00&amp;dn=Teargas+and+Plateglass-+Self-Titled+album+and+Black+Triage&amp;tr=udp%3A%2F%2Ftracker.openbittorrent.com%3A80&amp;tr=udp%3A%2F%2Fopen.demonii.com%3A1337&amp;tr=udp%3A%2F%2Ftracker.coppersurfer.tk%3A6969&amp;tr=udp%3A%2F%2Fexodus.desync.com%3A6969","seeders":0,"leechers":1,"uploader":"IvoryMask","files":28,"time":1304297106,"description":"Teargas and Plateglass\\\\\\'s two albums.  They weren\\\\\\'t up so I uploaded them.  I don\\\\\\'t know the bitrate or any of that.  The tags on the songs may be bad.  But you can listen to the songs.  Plus you can\\\\\\'t buy their self titled album on itunes or stores or amazon or anywhere that I know of.  Use the torrent however you like, maybe re-uploading it with specs.","torrent":{"xt":"urn:btih:2a33e25f18ece2ac5cd417935d627bbf303ffd00","amp;dn":"Teargas+and+Plateglass-+Self-Titled+album+and+Black+Triage","amp;tr":["udp%3A%2F%2Ftracker.openbittorrent.com%3A80","udp%3A%2F%2Fopen.demonii.com%3A1337","udp%3A%2F%2Ftracker.coppersurfer.tk%3A6969","udp%3A%2F%2Fexodus.desync.com%3A6969"],"infoHash":"2a33e25f18ece2ac5cd417935d627bbf303ffd00","infoHashBuffer":{"type":"Buffer","data":[42,51,226,95,24,236,226,172,92,212,23,147,93,98,123,191,48,63,253,0]},"announce":[],"urlList":[]}}