{"title":"NHRA 2011 - 02 - Gainesville.wmv","uid":6457664,"size":2881346483,"categoryP":"video","categoryS":"hd___tv_shows","magnet":"?xt=urn:btih:34785e62a0dd8c1deb06fc2cc0e6d7b8b2fc6b95&amp;dn=NHRA+2011+-+02+-+Gainesville.wmv&amp;tr=udp%3A%2F%2Ftracker.openbittorrent.com%3A80&amp;tr=udp%3A%2F%2Fopen.demonii.com%3A1337&amp;tr=udp%3A%2F%2Ftracker.coppersurfer.tk%3A6969&amp;tr=udp%3A%2F%2Fexodus.desync.com%3A6969","seeders":0,"leechers":0,"uploader":"corboy","files":1,"time":1307635757,"description":"Round 2 of the 2011 NHRA Drag Racing Season, from Gainesville","torrent":{"xt":"urn:btih:34785e62a0dd8c1deb06fc2cc0e6d7b8b2fc6b95","amp;dn":"NHRA+2011+-+02+-+Gainesville.wmv","amp;tr":["udp%3A%2F%2Ftracker.openbittorrent.com%3A80","udp%3A%2F%2Fopen.demonii.com%3A1337","udp%3A%2F%2Ftracker.coppersurfer.tk%3A6969","udp%3A%2F%2Fexodus.desync.com%3A6969"],"infoHash":"34785e62a0dd8c1deb06fc2cc0e6d7b8b2fc6b95","infoHashBuffer":{"type":"Buffer","data":[52,120,94,98,160,221,140,29,235,6,252,44,192,230,215,184,178,252,107,149]},"announce":[],"urlList":[]}}