{"title":"VA-Grand Gallery Presents-Tokyo Luxury Lounge 3-CD-2008","uid":4999241,"size":115900214,"categoryP":"audio","categoryS":"music","magnet":"?xt=urn:btih:35deb16699cb5836cd746fff6e63911b98a8d763&amp;dn=VA-Grand+Gallery+Presents-Tokyo+Luxury+Lounge+3-CD-2008&amp;tr=udp%3A%2F%2Ftracker.openbittorrent.com%3A80&amp;tr=udp%3A%2F%2Fopen.demonii.com%3A1337&amp;tr=udp%3A%2F%2Ftracker.coppersurfer.tk%3A6969&amp;tr=udp%3A%2F%2Fexodus.desync.com%3A6969","seeders":0,"leechers":1,"uploader":"marcco","files":16,"time":1247433534,"description":"T R A C K  L i S T\n\n\n\n01. Chieko Kinbara -  if You Only (Kaskade Lounge M 06:24\n\n02. Daishi Dance Feat Kat Mcdowell - I Believe (Sec 07:42\n\n03. Cargo - Life is Sweet (Alternative Piano Mix)   06:40\n\n04. Yoko Ota Feat Heather Johnson, Terrance Downs - 06:38\n\n05. Studio Apartment Feat Ron Carroll - I'm in Love 07:44\n\n06. Yoichiro Ito - Come Down to My Place            06:27\n\n07. I-Dep - Believe (Who You Are Edit)              07:36\n\n08. Sound Around - Shooting Star (Floor Edit)       05:52\n\n09. Note Native - Daisy Love (Twilight Edit)        05:32\n\n10. Makai Feat Samanthe Nelson - Move Your Feelings 06:16\n\n11. Soul Source Production - Feels Like Home        06:46\n\n12. Coldfeet - I Don't Like Dancing (More Dancing M 06:14\n","torrent":{"xt":"urn:btih:35deb16699cb5836cd746fff6e63911b98a8d763","amp;dn":"VA-Grand+Gallery+Presents-Tokyo+Luxury+Lounge+3-CD-2008","amp;tr":["udp%3A%2F%2Ftracker.openbittorrent.com%3A80","udp%3A%2F%2Fopen.demonii.com%3A1337","udp%3A%2F%2Ftracker.coppersurfer.tk%3A6969","udp%3A%2F%2Fexodus.desync.com%3A6969"],"infoHash":"35deb16699cb5836cd746fff6e63911b98a8d763","infoHashBuffer":{"type":"Buffer","data":[53,222,177,102,153,203,88,54,205,116,111,255,110,99,145,27,152,168,215,99]},"announce":[],"urlList":[]}}