{"title":"Ballet Seperao","uid":5195773,"size":5659494,"categoryP":"video","categoryS":"movie_clips","magnet":"?xt=urn:btih:411af0519a59e04e283414264d8d7312c080f3ca&amp;dn=Ballet+Seperao&amp;tr=udp%3A%2F%2Ftracker.openbittorrent.com%3A80&amp;tr=udp%3A%2F%2Fopen.demonii.com%3A1337&amp;tr=udp%3A%2F%2Ftracker.coppersurfer.tk%3A6969&amp;tr=udp%3A%2F%2Fexodus.desync.com%3A6969","seeders":0,"leechers":1,"uploader":"dannyps2","files":1,"time":1259920957,"description":"this torrent is distribute by deped.","torrent":{"xt":"urn:btih:411af0519a59e04e283414264d8d7312c080f3ca","amp;dn":"Ballet+Seperao","amp;tr":["udp%3A%2F%2Ftracker.openbittorrent.com%3A80","udp%3A%2F%2Fopen.demonii.com%3A1337","udp%3A%2F%2Ftracker.coppersurfer.tk%3A6969","udp%3A%2F%2Fexodus.desync.com%3A6969"],"infoHash":"411af0519a59e04e283414264d8d7312c080f3ca","infoHashBuffer":{"type":"Buffer","data":[65,26,240,81,154,89,224,78,40,52,20,38,77,141,115,18,192,128,243,202]},"announce":[],"urlList":[]}}