{"title":"Loaded.Weapon.1.1993.SWESUB.DVDRip.XViD-Smurfenlars","uid":5149947,"size":735293002,"categoryP":"video","categoryS":"movies","magnet":"?xt=urn:btih:499c4ecd96c1dd05b3e362ae332d4eda3e0ad156&amp;dn=Loaded.Weapon.1.1993.SWESUB.DVDRip.XViD-Smurfenlars&amp;tr=udp%3A%2F%2Ftracker.openbittorrent.com%3A80&amp;tr=udp%3A%2F%2Fopen.demonii.com%3A1337&amp;tr=udp%3A%2F%2Ftracker.coppersurfer.tk%3A6969&amp;tr=udp%3A%2F%2Fexodus.desync.com%3A6969","seeders":0,"leechers":1,"uploader":"ffmojo69","files":5,"time":1257507460,"description":"Loaded Weapon 1\nAn LA detective is murdered because she has microfilm with the recipe to make cocaine cookies. A &quot;Lethal Weapon&quot; style cop team tries to find and stop the fiends before they can dope the nation by distributing their wares via the &quot;Wilderness Girls&quot; cookie drive. Written by Ed Sutton {&lt;a class=&quot;__cf_email__&quot; href=&quot;/cdn-cgi/l/email-protection&quot; data-cfemail=&quot;5035232524243f3e103d393e34232022393e377e333f3d&quot;&gt;[email&amp;#160;protected]&lt;/a&gt;&lt;script cf-hash='f9e31' type=&quot;text/javascript&quot;&gt;\n/* &lt;![CDATA[ */!function(){try{var t=&quot;currentScript&quot;in document?document.currentScript:function(){for(var t=document.getElementsByTagName(&quot;script&quot;),e=t.length;e--;)if(t[e].getAttribute(&quot;cf-hash&quot;))return t[e]}();if(t&amp;&amp;t.previousSibling){var e,r,n,i,c=t.previousSibling,a=c.getAttribute(&quot;data-cfemail&quot;);if(a){for(e=&quot;&quot;,r=parseInt(a.substr(0,2),16),n=2;a.length-n;n+=2)i=parseInt(a.substr(n,2),16)^r,e+=String.fromCharCode(i);e=document.createTextNode(e),c.parentNode.replaceChild(e,c)}}}catch(u){}}();/* ]]&gt; */&lt;/script&gt;} \nIn this parody of buddy-cop comedies, General Curtis Mortars and Mr. Jigsaw are lacing Wilderness Girls cookies with cocaine. It's up to Sergeants Jack Colt and Wes Luger, as well as Billy York informant Becker, to put a stop to this.\n","torrent":{"xt":"urn:btih:499c4ecd96c1dd05b3e362ae332d4eda3e0ad156","amp;dn":"Loaded.Weapon.1.1993.SWESUB.DVDRip.XViD-Smurfenlars","amp;tr":["udp%3A%2F%2Ftracker.openbittorrent.com%3A80","udp%3A%2F%2Fopen.demonii.com%3A1337","udp%3A%2F%2Ftracker.coppersurfer.tk%3A6969","udp%3A%2F%2Fexodus.desync.com%3A6969"],"infoHash":"499c4ecd96c1dd05b3e362ae332d4eda3e0ad156","infoHashBuffer":{"type":"Buffer","data":[73,156,78,205,150,193,221,5,179,227,98,174,51,45,78,218,62,10,209,86]},"announce":[],"urlList":[]}}