{"title":"Fekete David - Ebredj fel!","uid":6403828,"size":74176983,"categoryP":"audio","categoryS":"music","magnet":"?xt=urn:btih:6ae03c4d76b4b0daae4a27f42f8d18f0ff72d302&amp;dn=Fekete+David+-+Ebredj+fel%21&amp;tr=udp%3A%2F%2Ftracker.openbittorrent.com%3A80&amp;tr=udp%3A%2F%2Fopen.demonii.com%3A1337&amp;tr=udp%3A%2F%2Ftracker.coppersurfer.tk%3A6969&amp;tr=udp%3A%2F%2Fexodus.desync.com%3A6969","seeders":0,"leechers":1,"uploader":null,"files":13,"time":1305743161,"description":"Track Listing\n-------------\n 1. Ãƒ","torrent":{"xt":"urn:btih:6ae03c4d76b4b0daae4a27f42f8d18f0ff72d302","amp;dn":"Fekete+David+-+Ebredj+fel%21","amp;tr":["udp%3A%2F%2Ftracker.openbittorrent.com%3A80","udp%3A%2F%2Fopen.demonii.com%3A1337","udp%3A%2F%2Ftracker.coppersurfer.tk%3A6969","udp%3A%2F%2Fexodus.desync.com%3A6969"],"infoHash":"6ae03c4d76b4b0daae4a27f42f8d18f0ff72d302","infoHashBuffer":{"type":"Buffer","data":[106,224,60,77,118,180,176,218,174,74,39,244,47,141,24,240,255,114,211,2]},"announce":[],"urlList":[]}}