{"title":"Best of 1999 Promo Only (Vob files) [Video Album]","uid":5150694,"size":8028292973,"categoryP":"video","categoryS":"music_videos","magnet":"?xt=urn:btih:6f089eb175b1e6e451f309f367627e39fe161fed&amp;dn=Best+of+1999+Promo+Only+%28Vob+files%29+%5BVideo+Album%5D&amp;tr=udp%3A%2F%2Ftracker.openbittorrent.com%3A80&amp;tr=udp%3A%2F%2Fopen.demonii.com%3A1337&amp;tr=udp%3A%2F%2Ftracker.coppersurfer.tk%3A6969&amp;tr=udp%3A%2F%2Fexodus.desync.com%3A6969","seeders":0,"leechers":1,"uploader":"towerelect","files":43,"time":1257539603,"description":"RE SEED to get rid of the now sadly defunct Demonoid tracker.\n\nSource Promo Only DVD9 Ripped into tracks using DVD Deycrypter Cell ID mode, please see torrent file names for track details:\n\nVob (mpeg2) files renamed using industry conventions\n320kps Stereo\nMixed screen ratio's\n\nEnjoy.\n\nRigmar Radio","torrent":{"xt":"urn:btih:6f089eb175b1e6e451f309f367627e39fe161fed","amp;dn":"Best+of+1999+Promo+Only+%28Vob+files%29+%5BVideo+Album%5D","amp;tr":["udp%3A%2F%2Ftracker.openbittorrent.com%3A80","udp%3A%2F%2Fopen.demonii.com%3A1337","udp%3A%2F%2Ftracker.coppersurfer.tk%3A6969","udp%3A%2F%2Fexodus.desync.com%3A6969"],"infoHash":"6f089eb175b1e6e451f309f367627e39fe161fed","infoHashBuffer":{"type":"Buffer","data":[111,8,158,177,117,177,230,228,81,243,9,243,103,98,126,57,254,22,31,237]},"announce":[],"urlList":[]}}