{"title":"RectalDestroyer.com - LARIN","uid":5157146,"size":612730238,"categoryP":"porn","categoryS":"movies","magnet":"?xt=urn:btih:74324482dae0e6a7eddae8d0263903beb489f068&amp;dn=RectalDestroyer.com+-+LARIN&amp;tr=udp%3A%2F%2Ftracker.openbittorrent.com%3A80&amp;tr=udp%3A%2F%2Fopen.demonii.com%3A1337&amp;tr=udp%3A%2F%2Ftracker.coppersurfer.tk%3A6969&amp;tr=udp%3A%2F%2Fexodus.desync.com%3A6969","seeders":0,"leechers":0,"uploader":"gnice06","files":-1,"time":1257924690,"description":"RectalDestroyer.com - LARIN\n\n\nLarin was selling Girl Scout cookies, but her potential customer was more interested in nookie than cookies! He takes her into his home and fucks the skank Scout so furiously she cries out in ecstasy and nearly blacks out from the sheer blacks out!\n\n\nScreens:\n &lt;a href=&quot;\nhttp://cache.imagefap.com/images/full/42/690/690968501.jpg&quot; rel=&quot;nofollow&quot; target=&quot;_NEW&quot;&gt;\nhttp://cache.imagefap.com/images/full/42/690/690968501.jpg&lt;/a&gt;\n\n\n\nMore Downloads Here:\n      &lt;a href=&quot;\nhttp://thepiratebay.se/user/gnice06&quot; rel=&quot;nofollow&quot; target=&quot;_NEW&quot;&gt;\nhttp://thepiratebay.se/user/gnice06&lt;/a&gt;","torrent":{"xt":"urn:btih:74324482dae0e6a7eddae8d0263903beb489f068","amp;dn":"RectalDestroyer.com+-+LARIN","amp;tr":["udp%3A%2F%2Ftracker.openbittorrent.com%3A80","udp%3A%2F%2Fopen.demonii.com%3A1337","udp%3A%2F%2Ftracker.coppersurfer.tk%3A6969","udp%3A%2F%2Fexodus.desync.com%3A6969"],"infoHash":"74324482dae0e6a7eddae8d0263903beb489f068","infoHashBuffer":{"type":"Buffer","data":[116,50,68,130,218,224,230,167,237,218,232,208,38,57,3,190,180,137,240,104]},"announce":[],"urlList":[]}}