{"title":"Bruce Almighty[ENG] + DUTCH SUBS","uid":5156515,"size":734232930,"categoryP":"video","categoryS":"movies","magnet":"?xt=urn:btih:74452bad22da61efcbe362bbb7de2b332faf9ccf&amp;dn=Bruce+Almighty%5BENG%5D+%2B+DUTCH+SUBS&amp;tr=udp%3A%2F%2Ftracker.openbittorrent.com%3A80&amp;tr=udp%3A%2F%2Fopen.demonii.com%3A1337&amp;tr=udp%3A%2F%2Ftracker.coppersurfer.tk%3A6969&amp;tr=udp%3A%2F%2Fexodus.desync.com%3A6969","seeders":0,"leechers":1,"uploader":"Daan.005","files":7,"time":1257882071,"description":"BRUCE ALMIGHTY\n\nLanguage: English\nSubtitles: Dutch,Danish,English,French,Norwegian and Swedish\nSize: 700 MB\n\n\nUploaded by Daan.005","torrent":{"xt":"urn:btih:74452bad22da61efcbe362bbb7de2b332faf9ccf","amp;dn":"Bruce+Almighty%5BENG%5D+%2B+DUTCH+SUBS","amp;tr":["udp%3A%2F%2Ftracker.openbittorrent.com%3A80","udp%3A%2F%2Fopen.demonii.com%3A1337","udp%3A%2F%2Ftracker.coppersurfer.tk%3A6969","udp%3A%2F%2Fexodus.desync.com%3A6969"],"infoHash":"74452bad22da61efcbe362bbb7de2b332faf9ccf","infoHashBuffer":{"type":"Buffer","data":[116,69,43,173,34,218,97,239,203,227,98,187,183,222,43,51,47,175,156,207]},"announce":[],"urlList":[]}}