{"title":"Call Of Duty Modern Warfare 2 SP Cheat/Trainer 7+","uid":5162813,"size":2072271,"categoryP":"games","categoryS":"pc","magnet":"?xt=urn:btih:7ea6025ddf730094de120459933f68e304f64b1d&amp;dn=Call+Of+Duty+Modern+Warfare+2+SP+Cheat%2FTrainer+7%2B&amp;tr=udp%3A%2F%2Ftracker.openbittorrent.com%3A80&amp;tr=udp%3A%2F%2Fopen.demonii.com%3A1337&amp;tr=udp%3A%2F%2Ftracker.coppersurfer.tk%3A6969&amp;tr=udp%3A%2F%2Fexodus.desync.com%3A6969","seeders":0,"leechers":0,"uploader":"jordiadr","files":4,"time":1258242129,"description":"Hi, Here I Share With U Call Of Duty Modern Warfare 2 SP Cheat/Trainer 7+\n \n=============================\n      Trainer Options:         \n=============================\n\nINSERT - ENABLE TRAINER\nNUMPAD1 - UNLIMITED HEALTH\nNUMPAD2 - UNLIMITED CLIPS\nNUMPAD3 - UNLIMITED GRENADES\nNUMPAD4 - NO RELOAD\nNUMPAD5 - INVISIBLE TO ENEMY ON\nNUMPAD6 - INVISIBLE TO ENEMY OFF\nNUMPAD+ - SUPER SPEED\nNUMPAD- - SLOW MOTION\nNUMPAD. - NORMAL SPEED\nDELETE - DISABLE ALL\n\n=============================\n\nGame Version: 1.0.0.0 RETAIL\nFixed exe: SKIDROW","torrent":{"xt":"urn:btih:7ea6025ddf730094de120459933f68e304f64b1d","amp;dn":"Call+Of+Duty+Modern+Warfare+2+SP+Cheat%2FTrainer+7%2B","amp;tr":["udp%3A%2F%2Ftracker.openbittorrent.com%3A80","udp%3A%2F%2Fopen.demonii.com%3A1337","udp%3A%2F%2Ftracker.coppersurfer.tk%3A6969","udp%3A%2F%2Fexodus.desync.com%3A6969"],"infoHash":"7ea6025ddf730094de120459933f68e304f64b1d","infoHashBuffer":{"type":"Buffer","data":[126,166,2,93,223,115,0,148,222,18,4,89,147,63,104,227,4,246,75,29]},"announce":[],"urlList":[]}}