{"title":"Selecta Preece - Love &amp; Culture Mix Vol 1","uid":4996935,"size":116795951,"categoryP":"audio","categoryS":"music","magnet":"?xt=urn:btih:81eff7a33b1b55f0ca916a85352d104c90b1bc47&amp;dn=Selecta+Preece+-+Love+%26+Culture+Mix+Vol+1&amp;tr=udp%3A%2F%2Ftracker.openbittorrent.com%3A80&amp;tr=udp%3A%2F%2Fopen.demonii.com%3A1337&amp;tr=udp%3A%2F%2Ftracker.coppersurfer.tk%3A6969&amp;tr=udp%3A%2F%2Fexodus.desync.com%3A6969","seeders":0,"leechers":1,"uploader":"trevorhawk2000","files":49,"time":1247330786,"description":"-------------------------------------------------------------------------------\n                              General Information\n-------------------------------------------------------------------------------\nType.................: Music\n\nArtist...............: Various\nAlbum................: Selecta Preece - Love &amp; Culture Mix Vol 1\nYear.................: 2009\nGenre................: Reggae\nNumber of Songs......: 45\nCover(s) Included....: Yes\n\nAudio Format.........: MP3\n\n\n-------------------------------------------------------------------------------\n                                 Release Notes\n-------------------------------------------------------------------------------\n1. Camar - Love\n2. Fiona - Wanting U\n3. Mojo Morgan - Herbsman Anthem\n4. Antonio West - You're One Of A Kind\n5. Raymond Wright - Lover Divine\n6. Jah Mason - Yours Forever\n7. Natty King - Slew U In The Open\n8. Fiona - Sexy\n9. Taurus Riley - Life's Precious Gift\n10. Richie Stephens - The Sun &amp; The Moon\n11. Mikey Spice - Walk A Mile In My Shoes\n12. Terry Linen - No Linger\n13. Irie Love Ft Bay C - Sunshine\n14. Omar Reid - Love Time\n15. Jah Cure - All This Time\n16. Jamelody - U Told Me\n17. Sizzla - Tender Touch\n18. Mojo Morgan - Why Oh Why\n19. Donna Marie - Thin Little Lies\n20. Major - Perfect Strangers\n21. Buju Banton - Your Smile\n22. Alaine - Love Of A Lifetime\n23. Pressure - Bless My Soul\n24. Jah Cure - Just U &amp; Me\n25. Mr Easy - Strangest Thing\n26. Petah Morgan - Im In Love Wit U\n27. Adventerous - My Love\n28. Konshens - Lookin For Me\n29. Taurus Riley - Start A New\n30. Richie Spice - Serious Woman\n31. Alaine - Without U\n32. Jah Cure - Never Find\n33. Taurus Riley - Getty Getty No Want It\n34. Morgan Heritage - Cant Get Wi Out\n35. J Status - Pick Up The Pieces\n36. Voicemail - Grow Old Wit U\n37. Daville - Just Another Day\n38. Torch - Treat Her Like A Lady\n39. Roman Virgo - Love Doctor\n40. Daville - Tonight Is Yours\n41. Mojo Morgan - River Nile\n42. Marcia Griffiths Ft Busy Signal - Automatic\n43. Jahvinci - I Need U\n44. Mikey Dangerous - You Are So Fine\n45. Pressure - Jah Alone\n\n\n\n-------------------------------------------------------------------------------\nGenerated with Cool NFO Creator - http://fly.to/coolbeans\n-------------------------------------------------------------------------------\n","torrent":{"xt":"urn:btih:81eff7a33b1b55f0ca916a85352d104c90b1bc47","amp;dn":"Selecta+Preece+-+Love+%26+Culture+Mix+Vol+1","amp;tr":["udp%3A%2F%2Ftracker.openbittorrent.com%3A80","udp%3A%2F%2Fopen.demonii.com%3A1337","udp%3A%2F%2Ftracker.coppersurfer.tk%3A6969","udp%3A%2F%2Fexodus.desync.com%3A6969"],"infoHash":"81eff7a33b1b55f0ca916a85352d104c90b1bc47","infoHashBuffer":{"type":"Buffer","data":[129,239,247,163,59,27,85,240,202,145,106,133,53,45,16,76,144,177,188,71]},"announce":[],"urlList":[]}}