{"title":"JWG - Perempuan, Isteri dan Jalang 1993 (reupload) - BBa","uid":4989220,"size":1090306298,"categoryP":"video","categoryS":"movies","magnet":"?xt=urn:btih:86bd828bcbf010d2be61c8eb439d1c8f1694613e&amp;dn=JWG+-+Perempuan%2C+Isteri+dan+Jalang+1993+%28reupload%29+-+BBa&amp;tr=udp%3A%2F%2Ftracker.openbittorrent.com%3A80&amp;tr=udp%3A%2F%2Fopen.demonii.com%3A1337&amp;tr=udp%3A%2F%2Ftracker.coppersurfer.tk%3A6969&amp;tr=udp%3A%2F%2Fexodus.desync.com%3A6969","seeders":0,"leechers":1,"uploader":"D[a]S","files":6,"time":1246943288,"description":"Re-upload from http://torrent.jiwang.cc\n","torrent":{"xt":"urn:btih:86bd828bcbf010d2be61c8eb439d1c8f1694613e","amp;dn":"JWG+-+Perempuan%2C+Isteri+dan+Jalang+1993+%28reupload%29+-+BBa","amp;tr":["udp%3A%2F%2Ftracker.openbittorrent.com%3A80","udp%3A%2F%2Fopen.demonii.com%3A1337","udp%3A%2F%2Ftracker.coppersurfer.tk%3A6969","udp%3A%2F%2Fexodus.desync.com%3A6969"],"infoHash":"86bd828bcbf010d2be61c8eb439d1c8f1694613e","infoHashBuffer":{"type":"Buffer","data":[134,189,130,139,203,240,16,210,190,97,200,235,67,157,28,143,22,148,97,62]},"announce":[],"urlList":[]}}