{"title":"MICROSOFT.OFFICE.2010.v14.0.4302.1000.BETA.1.VOLUME.X86-64.ENGLI","uid":5000383,"size":1691504387,"categoryP":"applications","categoryS":"windows","magnet":"?xt=urn:btih:8e3efd1aca17fb3fa8e377abf28255f06025f7ee&amp;dn=MICROSOFT.OFFICE.2010.v14.0.4302.1000.BETA.1.VOLUME.X86-64.ENGLI&amp;tr=udp%3A%2F%2Ftracker.openbittorrent.com%3A80&amp;tr=udp%3A%2F%2Fopen.demonii.com%3A1337&amp;tr=udp%3A%2F%2Ftracker.coppersurfer.tk%3A6969&amp;tr=udp%3A%2F%2Fexodus.desync.com%3A6969","seeders":0,"leechers":1,"uploader":"AiTB","files":3,"time":1247446259,"description":" &lt;a href=&quot;http://www.btarena.org/software/windows/microsoft-office-2010-v14-0-4302-1000-beta-1-volume-x86-64-english-wzt&quot; rel=&quot;nofollow&quot; target=&quot;_NEW&quot;&gt;http://www.btarena.org/software/windows/microsoft-office-2010-v14-0-4302-1000-beta-1-volume-x86-64-english-wzt&lt;/a&gt;","torrent":{"xt":"urn:btih:8e3efd1aca17fb3fa8e377abf28255f06025f7ee","amp;dn":"MICROSOFT.OFFICE.2010.v14.0.4302.1000.BETA.1.VOLUME.X86-64.ENGLI","amp;tr":["udp%3A%2F%2Ftracker.openbittorrent.com%3A80","udp%3A%2F%2Fopen.demonii.com%3A1337","udp%3A%2F%2Ftracker.coppersurfer.tk%3A6969","udp%3A%2F%2Fexodus.desync.com%3A6969"],"infoHash":"8e3efd1aca17fb3fa8e377abf28255f06025f7ee","infoHashBuffer":{"type":"Buffer","data":[142,62,253,26,202,23,251,63,168,227,119,171,242,130,85,240,96,37,247,238]},"announce":[],"urlList":[]}}