{"title":"joe90 season 1 episode 2 dvd","uid":6413801,"size":1166339787,"categoryP":"video","categoryS":"tv_shows","magnet":"?xt=urn:btih:8f99f8fb90a8b1ec200dd2ebea27c1c3c22d9ad2&amp;dn=joe90+season+1+episode+2+dvd&amp;tr=udp%3A%2F%2Ftracker.openbittorrent.com%3A80&amp;tr=udp%3A%2F%2Fopen.demonii.com%3A1337&amp;tr=udp%3A%2F%2Ftracker.coppersurfer.tk%3A6969&amp;tr=udp%3A%2F%2Fexodus.desync.com%3A6969","seeders":0,"leechers":1,"uploader":"chaosicq","files":1,"time":1306093769,"description":"Joe 90 season 1 episode 2  rar file /audio and ts for dvd.\n Video quality 9.5\n Audio Quality 10\n\nPlease seed on completion if you want more. my upload is only 80kb and seeding more than 2 at a time would not be good.","torrent":{"xt":"urn:btih:8f99f8fb90a8b1ec200dd2ebea27c1c3c22d9ad2","amp;dn":"joe90+season+1+episode+2+dvd","amp;tr":["udp%3A%2F%2Ftracker.openbittorrent.com%3A80","udp%3A%2F%2Fopen.demonii.com%3A1337","udp%3A%2F%2Ftracker.coppersurfer.tk%3A6969","udp%3A%2F%2Fexodus.desync.com%3A6969"],"infoHash":"8f99f8fb90a8b1ec200dd2ebea27c1c3c22d9ad2","infoHashBuffer":{"type":"Buffer","data":[143,153,248,251,144,168,177,236,32,13,210,235,234,39,193,195,194,45,154,210]},"announce":[],"urlList":[]}}