{"title":"brunettebride silverdust.avi","uid":5104570,"size":239607738,"categoryP":"porn","categoryS":"movie_clips","magnet":"?xt=urn:btih:9686e0a42799624545568fcc5ec35f30c71400d2&amp;dn=brunettebride+silverdust.avi&amp;tr=udp%3A%2F%2Ftracker.openbittorrent.com%3A80&amp;tr=udp%3A%2F%2Fopen.demonii.com%3A1337&amp;tr=udp%3A%2F%2Ftracker.coppersurfer.tk%3A6969&amp;tr=udp%3A%2F%2Fexodus.desync.com%3A6969","seeders":0,"leechers":0,"uploader":"dodgerblue","files":1,"time":1254260462,"description":"brunettebride silverdust\nNew bride takes on hubby and best man\nFlash preview turn ya speakers up! [url]http://www.swfcabin.com/open/1254248639[/url]\n&quot;I gotta get through this&quot;-D bedingfield\n[url]http://www.fhqhosting.com/ui/1ggggg.swf[/url]\n[IMG]http://i43.servimg.com/u/f43/12/33/79/02/potpis10.gif[/IMG]\n[IMG]http://www.myspaceninja.com/images/gg/glitterhkisses.gif[/IMG]","torrent":{"xt":"urn:btih:9686e0a42799624545568fcc5ec35f30c71400d2","amp;dn":"brunettebride+silverdust.avi","amp;tr":["udp%3A%2F%2Ftracker.openbittorrent.com%3A80","udp%3A%2F%2Fopen.demonii.com%3A1337","udp%3A%2F%2Ftracker.coppersurfer.tk%3A6969","udp%3A%2F%2Fexodus.desync.com%3A6969"],"infoHash":"9686e0a42799624545568fcc5ec35f30c71400d2","infoHashBuffer":{"type":"Buffer","data":[150,134,224,164,39,153,98,69,69,86,143,204,94,195,95,48,199,20,0,210]},"announce":[],"urlList":[]}}