{"title":"brandon heath - trust you","uid":5182478,"size":9657312,"categoryP":"audio","categoryS":"music","magnet":"?xt=urn:btih:9dbac5b1a941a2a20f635a3b51c942e125258b86&amp;dn=brandon+heath+-+trust+you&amp;tr=udp%3A%2F%2Ftracker.openbittorrent.com%3A80&amp;tr=udp%3A%2F%2Fopen.demonii.com%3A1337&amp;tr=udp%3A%2F%2Ftracker.coppersurfer.tk%3A6969&amp;tr=udp%3A%2F%2Fexodus.desync.com%3A6969","seeders":0,"leechers":1,"uploader":null,"files":3,"time":1259313911,"description":"brandon heath","torrent":{"xt":"urn:btih:9dbac5b1a941a2a20f635a3b51c942e125258b86","amp;dn":"brandon+heath+-+trust+you","amp;tr":["udp%3A%2F%2Ftracker.openbittorrent.com%3A80","udp%3A%2F%2Fopen.demonii.com%3A1337","udp%3A%2F%2Ftracker.coppersurfer.tk%3A6969","udp%3A%2F%2Fexodus.desync.com%3A6969"],"infoHash":"9dbac5b1a941a2a20f635a3b51c942e125258b86","infoHashBuffer":{"type":"Buffer","data":[157,186,197,177,169,65,162,162,15,99,90,59,81,201,66,225,37,37,139,134]},"announce":[],"urlList":[]}}