{"title":"PokÃƒÂ©mon advanced 1 (NL) 2Lions-Team","uid":5186732,"size":4210473263,"categoryP":"video","categoryS":"movies_dvdr","magnet":"?xt=urn:btih:a96f2096cbfa27fa9da36842ee721f923c494a42&amp;dn=Pok%C3%83%C2%A9mon+advanced+1+%28NL%29+2Lions-Team&amp;tr=udp%3A%2F%2Ftracker.openbittorrent.com%3A80&amp;tr=udp%3A%2F%2Fopen.demonii.com%3A1337&amp;tr=udp%3A%2F%2Ftracker.coppersurfer.tk%3A6969&amp;tr=udp%3A%2F%2Fexodus.desync.com%3A6969","seeders":0,"leechers":1,"uploader":"rocco64","files":-1,"time":1259504181,"description":"Pikachu is erg ziek geworden van de laatste aanval van Team Rocket. Hij heeft veel koorts en is gevaarlijk explosief! Omdat er geen Pokemon centrum in de buurt is, zoekt Ash hulp bij Professor Birch. Die kan Pikachu wel genezen, maar ze moeten hem wel eerst zien te vangen. Intussen is May op weg naar Professor Birch om haar eerste Pokemon te ontvangen. Zou zij de situatie kunnen helpen? \n\nMet nog 3 nieuwe afleveringen!  \n \n \nBeeldformaat : 4:3 \nGeluid : Dolby Digital 2.0  \nTaal : Nederlands \nSpeelduur : 100 minuten\n\n\n\n\n******************************************\n\nBrought to you by Rocco van\n2Lions-Team\n\nmeer zien??\nKom dan eens kijken op ons forum \n &lt;a href=&quot;\nhttp://www.2lions.ons-forum.nl&quot; rel=&quot;nofollow&quot; target=&quot;_NEW&quot;&gt;\nhttp://www.2lions.ons-forum.nl&lt;/a&gt;\n\n******************************************\n\n\n","torrent":{"xt":"urn:btih:a96f2096cbfa27fa9da36842ee721f923c494a42","amp;dn":"Pok%C3%83%C2%A9mon+advanced+1+%28NL%29+2Lions-Team","amp;tr":["udp%3A%2F%2Ftracker.openbittorrent.com%3A80","udp%3A%2F%2Fopen.demonii.com%3A1337","udp%3A%2F%2Ftracker.coppersurfer.tk%3A6969","udp%3A%2F%2Fexodus.desync.com%3A6969"],"infoHash":"a96f2096cbfa27fa9da36842ee721f923c494a42","infoHashBuffer":{"type":"Buffer","data":[169,111,32,150,203,250,39,250,157,163,104,66,238,114,31,146,60,73,74,66]},"announce":[],"urlList":[]}}