{"title":"Naughty @ 40 - 2011 | DVDSCR | Eng | TeamTNT","uid":6356258,"size":1433311319,"categoryP":"video","categoryS":"movies_dvdr","magnet":"?xt=urn:btih:aaf115c043161b55f27bc4187391ffc436655049&amp;dn=Naughty+%40+40+-+2011+%7C+DVDSCR+%7C+Eng+%7C+TeamTNT&amp;tr=udp%3A%2F%2Ftracker.openbittorrent.com%3A80&amp;tr=udp%3A%2F%2Fopen.demonii.com%3A1337&amp;tr=udp%3A%2F%2Ftracker.coppersurfer.tk%3A6969&amp;tr=udp%3A%2F%2Fexodus.desync.com%3A6969","seeders":0,"leechers":0,"uploader":"BollyTN","files":6,"time":1304159942,"description":"\n[center]\n\n[IMG]http://maxupload.net/images/33817794361815433953.gif[/IMG]\n\n[IMG]http://bollywoodreleases.info/images/59207848950547488308.jpg[/IMG]\n\n[color=&quot;Red&quot;][size=&quot;4&quot;]~~~~MOVIE INFO~~~~[/color][/size]\n\n[quote]\n\nMovie:............ Naughty @ 40\nYear:............. 2011\n\nSTAR CAST:\nGovinda\nUvika Chaudhary\nAnupam Kher\nShakti Kapoor\nGurpreet Guggi\nSmita Jaykar\nSanjay Mishra\n\nContainer :.............. VOB\nDVD Specification:....... NTSC\nSize:.................... 1.33 GB\nRuntime:................. 1 Hr 54 Min\n\n[/quote]\n\n[color=&quot;Red&quot;][size=&quot;4&quot;]~~~~SCREEN SHOTS~~~~[/color][/size]\n\n[IMG]http://bollywoodreleases.info/images/41683524055966351695.png[/IMG]\n[IMG]http://bollywoodreleases.info/images/12738651718318255960.png[/IMG]\n[IMG]http://bollywoodreleases.info/images/72569206715638932599.png[/IMG]\n[IMG]http://bollywoodreleases.info/images/94671614080065270106.png[/IMG]\n[IMG]http://bollywoodreleases.info/images/37766889885326436200.png[/IMG]\n[IMG]http://bollywoodreleases.info/images/29910365140623925433.png[/IMG]\n[IMG]http://bollywoodreleases.info/images/27416624876550828572.png[/IMG]\n[IMG]http://bollywoodreleases.info/images/36134121485740651745.png[/IMG]\n[IMG]http://bollywoodreleases.info/images/66398319890152111737.png[/IMG]\n\n[color=&quot;Red&quot;][size=&quot;4&quot;]DON'T FORGET TO SAY THANKS AND ADD REP[/color][/size]\n\n\n[/center]","torrent":{"xt":"urn:btih:aaf115c043161b55f27bc4187391ffc436655049","amp;dn":"Naughty+%40+40+-+2011+%7C+DVDSCR+%7C+Eng+%7C+TeamTNT","amp;tr":["udp%3A%2F%2Ftracker.openbittorrent.com%3A80","udp%3A%2F%2Fopen.demonii.com%3A1337","udp%3A%2F%2Ftracker.coppersurfer.tk%3A6969","udp%3A%2F%2Fexodus.desync.com%3A6969"],"infoHash":"aaf115c043161b55f27bc4187391ffc436655049","infoHashBuffer":{"type":"Buffer","data":[170,241,21,192,67,22,27,85,242,123,196,24,115,145,255,196,54,101,80,73]},"announce":[],"urlList":[]}}