{"title":"El.Canto.Del.Loco.-.Radio.La.Colifata.Bonus.Videoclip.320Kbps.Fu","uid":5179526,"size":301107293,"categoryP":"audio","categoryS":"music","magnet":"?xt=urn:btih:b488c3a305bd3312fcfd7f2017e3b653c65ae86e&amp;dn=El.Canto.Del.Loco.-.Radio.La.Colifata.Bonus.Videoclip.320Kbps.Fu&amp;tr=udp%3A%2F%2Ftracker.openbittorrent.com%3A80&amp;tr=udp%3A%2F%2Fopen.demonii.com%3A1337&amp;tr=udp%3A%2F%2Ftracker.coppersurfer.tk%3A6969&amp;tr=udp%3A%2F%2Fexodus.desync.com%3A6969","seeders":0,"leechers":1,"uploader":"LDivx","files":31,"time":1259165574,"description":"Fecha Lanzamiento: 24/11/2009 \n\nEstilo: Pop-Rock \n\nTracklist:\n\n01. Un millon de cicatrices\n02. Ya nada volvera a ser como antes\n03. Quiero aprender de ti\n04. Volvera (con Alejandro sanz)\n05. Peter Pan\n06. Besos\n07. Corazon\n08. La madre de jose / sin documentos\n09. Eres tonto (con Vicentico)\n10. Puede ser\n11. Zapatillas\n12. Canciones\n13. Personas\n14. Contigo (con Natalia Lafurcade)\n15. LLueve en mi\n16. Pescao\n17. La suerte de mi vida\n18. Una foto en blanco y negro\n19. Fin de semana\n20. Peter Pan (con Leiva de Pereza)\n\nBonustrack:\n\n01. El.Canto.Del.Loco.-.Quiero.Aprender.De.Ti.HDRIP.2009","torrent":{"xt":"urn:btih:b488c3a305bd3312fcfd7f2017e3b653c65ae86e","amp;dn":"El.Canto.Del.Loco.-.Radio.La.Colifata.Bonus.Videoclip.320Kbps.Fu","amp;tr":["udp%3A%2F%2Ftracker.openbittorrent.com%3A80","udp%3A%2F%2Fopen.demonii.com%3A1337","udp%3A%2F%2Ftracker.coppersurfer.tk%3A6969","udp%3A%2F%2Fexodus.desync.com%3A6969"],"infoHash":"b488c3a305bd3312fcfd7f2017e3b653c65ae86e","infoHashBuffer":{"type":"Buffer","data":[180,136,195,163,5,189,51,18,252,253,127,32,23,227,182,83,198,90,232,110]},"announce":[],"urlList":[]}}