{"title":"Olga.wmv","uid":5191966,"size":376532493,"categoryP":"porn","categoryS":"movie_clips","magnet":"?xt=urn:btih:c3d1befe2ed67750bd21cce972d4c7e27d7e23aa&amp;dn=Olga.wmv&amp;tr=udp%3A%2F%2Ftracker.openbittorrent.com%3A80&amp;tr=udp%3A%2F%2Fopen.demonii.com%3A1337&amp;tr=udp%3A%2F%2Ftracker.coppersurfer.tk%3A6969&amp;tr=udp%3A%2F%2Fexodus.desync.com%3A6969","seeders":0,"leechers":0,"uploader":"Puzker","files":-1,"time":1259714915,"description":"Olga gets in the ass\nAss was very inhospitable and long resisted the penetration but still fell under the onslaught &lt;a href=&quot;\nhttp://honeyass.net/&quot; rel=&quot;nofollow&quot; target=&quot;_NEW&quot;&gt;\nhttp://honeyass.net/&lt;/a&gt;\nTech. Data:\nFormat: WMV\nDuration; 00:19:30\nAudio: Windows Media Audio 48000Hz stereo 192Kbps\nVideo: Windows Media Video 9 800x452 29.97fps 2367Kbps","torrent":{"xt":"urn:btih:c3d1befe2ed67750bd21cce972d4c7e27d7e23aa","amp;dn":"Olga.wmv","amp;tr":["udp%3A%2F%2Ftracker.openbittorrent.com%3A80","udp%3A%2F%2Fopen.demonii.com%3A1337","udp%3A%2F%2Ftracker.coppersurfer.tk%3A6969","udp%3A%2F%2Fexodus.desync.com%3A6969"],"infoHash":"c3d1befe2ed67750bd21cce972d4c7e27d7e23aa","infoHashBuffer":{"type":"Buffer","data":[195,209,190,254,46,214,119,80,189,33,204,233,114,212,199,226,125,126,35,170]},"announce":[],"urlList":[]}}