{"title":"Ningen no yakusoku aka A Promise","uid":5177958,"size":8257116160,"categoryP":"video","categoryS":"movies_dvdr","magnet":"?xt=urn:btih:c425d359b401a2b865e25b7c795ff19dc0fb7b96&amp;dn=Ningen+no+yakusoku+aka+A+Promise&amp;tr=udp%3A%2F%2Ftracker.openbittorrent.com%3A80&amp;tr=udp%3A%2F%2Fopen.demonii.com%3A1337&amp;tr=udp%3A%2F%2Ftracker.coppersurfer.tk%3A6969&amp;tr=udp%3A%2F%2Fexodus.desync.com%3A6969","seeders":0,"leechers":1,"uploader":"polifem2009","files":28,"time":1259080510,"description":" &lt;a href=&quot;http://www.imdb.com/title/tt0169085/&quot; rel=&quot;nofollow&quot; target=&quot;_NEW&quot;&gt;http://www.imdb.com/title/tt0169085/&lt;/a&gt;\n\n\n1986\nJAPAN\nDVD9\nVIDEO TS\nPAL\n1.66:1\nDD 2.0\nSUBTITLES: English, French\n\n\n\n\nDIRECTOR: YOSHIDA Kiju\n\n\nMIKUNI Rentaro\n\n","torrent":{"xt":"urn:btih:c425d359b401a2b865e25b7c795ff19dc0fb7b96","amp;dn":"Ningen+no+yakusoku+aka+A+Promise","amp;tr":["udp%3A%2F%2Ftracker.openbittorrent.com%3A80","udp%3A%2F%2Fopen.demonii.com%3A1337","udp%3A%2F%2Ftracker.coppersurfer.tk%3A6969","udp%3A%2F%2Fexodus.desync.com%3A6969"],"infoHash":"c425d359b401a2b865e25b7c795ff19dc0fb7b96","infoHashBuffer":{"type":"Buffer","data":[196,37,211,89,180,1,162,184,101,226,91,124,121,95,241,157,192,251,123,150]},"announce":[],"urlList":[]}}