{"title":"So.You.Think.You.Can.Dance.S08E01.Auditions.1.and.2.HDTV.XviD-FQ","uid":6425952,"size":734830236,"categoryP":"video","categoryS":"tv_shows","magnet":"?xt=urn:btih:c733b690e6da798b5e0cc2a4413259e56e44f428&amp;dn=So.You.Think.You.Can.Dance.S08E01.Auditions.1.and.2.HDTV.XviD-FQ&amp;tr=udp%3A%2F%2Ftracker.openbittorrent.com%3A80&amp;tr=udp%3A%2F%2Fopen.demonii.com%3A1337&amp;tr=udp%3A%2F%2Ftracker.coppersurfer.tk%3A6969&amp;tr=udp%3A%2F%2Fexodus.desync.com%3A6969","seeders":0,"leechers":1,"uploader":"torrentzone","files":39,"time":1306470727,"description":"Torrent Uploaded By https://torrentzone.net \n \n\nNOTE this sever does not have the power to extract effecently but i enoy sharing so i still upload \n\n\nLike this torrent? Come Join us at https://torrentzone.net/ For faster downloads, no fakes and NO RARS.\n\n\n We are Building a great community with many torrents AND FASTER DOWNLOADS. Uploads are fast and great quality!","torrent":{"xt":"urn:btih:c733b690e6da798b5e0cc2a4413259e56e44f428","amp;dn":"So.You.Think.You.Can.Dance.S08E01.Auditions.1.and.2.HDTV.XviD-FQ","amp;tr":["udp%3A%2F%2Ftracker.openbittorrent.com%3A80","udp%3A%2F%2Fopen.demonii.com%3A1337","udp%3A%2F%2Ftracker.coppersurfer.tk%3A6969","udp%3A%2F%2Fexodus.desync.com%3A6969"],"infoHash":"c733b690e6da798b5e0cc2a4413259e56e44f428","infoHashBuffer":{"type":"Buffer","data":[199,51,182,144,230,218,121,139,94,12,194,164,65,50,89,229,110,68,244,40]},"announce":[],"urlList":[]}}