{"title":"Ever.After.1998.SWESUB.DVDR","uid":5018561,"size":4681496261,"categoryP":"video","categoryS":"movies_dvdr","magnet":"?xt=urn:btih:d71d9db1bea65ca10fa4cbeb975f11af247acc73&amp;dn=Ever.After.1998.SWESUB.DVDR&amp;tr=udp%3A%2F%2Ftracker.openbittorrent.com%3A80&amp;tr=udp%3A%2F%2Fopen.demonii.com%3A1337&amp;tr=udp%3A%2F%2Ftracker.coppersurfer.tk%3A6969&amp;tr=udp%3A%2F%2Fexodus.desync.com%3A6969","seeders":0,"leechers":4,"uploader":"ff_poppe","files":3,"time":1248349976,"description":"Det var en gÃƒÂ¥ng... &quot;Askunge som ÃƒÂ¶veraskar&quot; (Svenska Dagbladet). HÃƒÂ¤r blir det blÃƒÂ¥st nytt liv i en urgammal legend och vi fÃƒÂ¥r tron tillbaka pÃƒÂ¥ den starkaste magin av alla: hjÃƒÂ¤rtats kraft. \nDrew Barrymore och Anjelica Huston spelar huvudrollerna i detta betagande ÃƒÂ¤ventyr om att ha modet att fÃƒÂ¶lja sina drÃƒÂ¶mmar. Den &quot;moderna&quot; unga 1500-talskvinnan Danielle (Barrymore) ÃƒÂ¤r lika oberoende och klok, som vacker och vÃƒÂ¤nlig. \nMot alla odds vÃƒÂ¥gar hon trotsa sin strÃƒÂ¤nga styvmoder (Huston) och utfÃƒÂ¶r mirakel fÃƒÂ¶r alla i sin omgivning, bland dem ÃƒÂ¤ven den franske kronprinsen (Dougray Scott)! \nNu kan du ÃƒÂ¥teruppleva den klassiska sagan i en totalt fÃƒÂ¤ngslande och samtida version. ","torrent":{"xt":"urn:btih:d71d9db1bea65ca10fa4cbeb975f11af247acc73","amp;dn":"Ever.After.1998.SWESUB.DVDR","amp;tr":["udp%3A%2F%2Ftracker.openbittorrent.com%3A80","udp%3A%2F%2Fopen.demonii.com%3A1337","udp%3A%2F%2Ftracker.coppersurfer.tk%3A6969","udp%3A%2F%2Fexodus.desync.com%3A6969"],"infoHash":"d71d9db1bea65ca10fa4cbeb975f11af247acc73","infoHashBuffer":{"type":"Buffer","data":[215,29,157,177,190,166,92,161,15,164,203,235,151,95,17,175,36,122,204,115]},"announce":[],"urlList":[]}}