{"title":"Deutsche Crunkheit","uid":4998741,"size":96696518,"categoryP":"audio","categoryS":"other","magnet":"?xt=urn:btih:d7223173766f5275349970f51090665a546c6d7b&amp;dn=Deutsche+Crunkheit&amp;tr=udp%3A%2F%2Ftracker.openbittorrent.com%3A80&amp;tr=udp%3A%2F%2Fopen.demonii.com%3A1337&amp;tr=udp%3A%2F%2Ftracker.coppersurfer.tk%3A6969&amp;tr=udp%3A%2F%2Fexodus.desync.com%3A6969","seeders":0,"leechers":1,"uploader":"Devil666mostwanted","files":1,"time":1247416918,"description":"Micoholic - Deutsche Crunkheit.","torrent":{"xt":"urn:btih:d7223173766f5275349970f51090665a546c6d7b","amp;dn":"Deutsche+Crunkheit","amp;tr":["udp%3A%2F%2Ftracker.openbittorrent.com%3A80","udp%3A%2F%2Fopen.demonii.com%3A1337","udp%3A%2F%2Ftracker.coppersurfer.tk%3A6969","udp%3A%2F%2Fexodus.desync.com%3A6969"],"infoHash":"d7223173766f5275349970f51090665a546c6d7b","infoHashBuffer":{"type":"Buffer","data":[215,34,49,115,118,111,82,117,52,153,112,245,16,144,102,90,84,108,109,123]},"announce":[],"urlList":[]}}