{"title":"Funny People UNRATED DVDRip x264 AAC 5.1 (basil.fawlty).mp4","uid":5163333,"size":1299262917,"categoryP":"video","categoryS":"movies","magnet":"?xt=urn:btih:ed45ff3a760d88cb5b7d3871d4b268497a00bd89&amp;dn=Funny+People+UNRATED+DVDRip+x264+AAC+5.1+%28basil.fawlty%29.mp4&amp;tr=udp%3A%2F%2Ftracker.openbittorrent.com%3A80&amp;tr=udp%3A%2F%2Fopen.demonii.com%3A1337&amp;tr=udp%3A%2F%2Ftracker.coppersurfer.tk%3A6969&amp;tr=udp%3A%2F%2Fexodus.desync.com%3A6969","seeders":0,"leechers":0,"uploader":"basil.fawlty","files":1,"time":1258281752,"description":"This is my 3rd upload your comments are important to me dont forget to seed when finished ENJOY\n","torrent":{"xt":"urn:btih:ed45ff3a760d88cb5b7d3871d4b268497a00bd89","amp;dn":"Funny+People+UNRATED+DVDRip+x264+AAC+5.1+%28basil.fawlty%29.mp4","amp;tr":["udp%3A%2F%2Ftracker.openbittorrent.com%3A80","udp%3A%2F%2Fopen.demonii.com%3A1337","udp%3A%2F%2Ftracker.coppersurfer.tk%3A6969","udp%3A%2F%2Fexodus.desync.com%3A6969"],"infoHash":"ed45ff3a760d88cb5b7d3871d4b268497a00bd89","infoHashBuffer":{"type":"Buffer","data":[237,69,255,58,118,13,136,203,91,125,56,113,212,178,104,73,122,0,189,137]},"announce":[],"urlList":[]}}