{"title":"Cyber Update Nov.2009------FM-7334  Phoenix Marie","uid":5166109,"size":818865303,"categoryP":"porn","categoryS":"movies","magnet":"?xt=urn:btih:f40f2de7e7bb13e767c68e5ecacf31b0b762b925&amp;dn=Cyber+Update+Nov.2009------FM-7334++Phoenix+Marie&amp;tr=udp%3A%2F%2Ftracker.openbittorrent.com%3A80&amp;tr=udp%3A%2F%2Fopen.demonii.com%3A1337&amp;tr=udp%3A%2F%2Ftracker.coppersurfer.tk%3A6969&amp;tr=udp%3A%2F%2Fexodus.desync.com%3A6969","seeders":0,"leechers":1,"uploader":"merzedes","files":274,"time":1258411337,"description":"From Kink.com      (Fuckingmachines) + Pics\t","torrent":{"xt":"urn:btih:f40f2de7e7bb13e767c68e5ecacf31b0b762b925","amp;dn":"Cyber+Update+Nov.2009------FM-7334++Phoenix+Marie","amp;tr":["udp%3A%2F%2Ftracker.openbittorrent.com%3A80","udp%3A%2F%2Fopen.demonii.com%3A1337","udp%3A%2F%2Ftracker.coppersurfer.tk%3A6969","udp%3A%2F%2Fexodus.desync.com%3A6969"],"infoHash":"f40f2de7e7bb13e767c68e5ecacf31b0b762b925","infoHashBuffer":{"type":"Buffer","data":[244,15,45,231,231,187,19,231,103,198,142,94,202,207,49,176,183,98,185,37]},"announce":[],"urlList":[]}}